ibson/__init__.py
ibson/codec_util.py
ibson/decoder.py
ibson/encoder.py
ibson/errors.py
ibson/tool/__init__.py
ibson/tool/bsonq.py
ibson/types.py
ibson-0.0.3.dist-info/LICENSE
ibson-0.0.3.dist-info/WHEEL
ibson-0.0.3.dist-info/METADATA
ibson-0.0.3.dist-info/RECORD
