Metadata-Version: 2.1
Name: ibson
Version: 0.0.3
Summary: BSON parsing library and tool.
Home-page: https://github.com/eulersIDcrisis/ibson
License: Apache-2.0
Author: Aaron Gibson
Author-email: eulersidcrisis@yahoo.com
Requires-Python: >=3.7,<4
Classifier: Development Status :: 3 - Alpha
Classifier: Intended Audience :: Developers
Classifier: License :: OSI Approved :: Apache Software License
Classifier: Programming Language :: Python :: 3
Classifier: Programming Language :: Python :: 3.10
Classifier: Programming Language :: Python :: 3.7
Classifier: Programming Language :: Python :: 3.8
Classifier: Programming Language :: Python :: 3.9
Project-URL: Bug Tracker, https://github.com/eulersIDcrisis/ibson/issues
Project-URL: Repository, https://github.com/eulersIDcrisis/ibson
